solaredge_web/__init__.py
solaredge_web/py.typed
solaredge_web/solaredge.py
solaredge_web-0.2.0.dist-info/licenses/LICENSE
solaredge_web-0.2.0.dist-info/METADATA
solaredge_web-0.2.0.dist-info/WHEEL
solaredge_web-0.2.0.dist-info/top_level.txt
solaredge_web-0.2.0.dist-info/RECORD
