Metadata-Version: 2.4
Name: solaredge-web
Version: 0.2.0
Summary: A python client library for SolarEdge Web
Author-email: tronikos <tronikos@gmail.com>
License-Expression: Apache-2.0
Project-URL: Homepage, https://github.com/tronikos/solaredge-web
Project-URL: Bug Tracker, https://github.com/tronikos/solaredge-web/issues
Requires-Python: >=3.10
License-File: LICENSE
Requires-Dist: aiohttp>=3.8
Provides-Extra: test
Requires-Dist: pytest; extra == "test"
Dynamic: license-file
